naapc/__init__.py
naapc/base.py
naapc/dict_traverse.py
naapc/ndict.py
naapc/snd.py
naapc/stop_conditions.py
naapc-2.1.2.dist-info/LICENSE
naapc-2.1.2.dist-info/METADATA
naapc-2.1.2.dist-info/WHEEL
naapc-2.1.2.dist-info/top_level.txt
naapc-2.1.2.dist-info/RECORD
