Metadata-Version: 2.1
Name: naapc
Version: 2.1.2
Summary: Nested Automated Argument Parsing Configuration (NAAPC).
Author-email: Bai Huanyu <eiphnix@gmail.com>
License: MIT License
Project-URL: repository, https://github.com/eiphy/naapc
Keywords: configuration,config,dictionary,nested,argument parsing
Classifier: License :: OSI Approved :: MIT License
Classifier: Programming Language :: Python
Classifier: Programming Language :: Python :: 3
Requires-Python: >=3.10
License-File: LICENSE
Requires-Dist: pyyaml
